scd30_i2c/__init__.py
scd30_i2c-0.0.6.dist-info/LICENSE
scd30_i2c-0.0.6.dist-info/METADATA
scd30_i2c-0.0.6.dist-info/WHEEL
scd30_i2c-0.0.6.dist-info/top_level.txt
scd30_i2c-0.0.6.dist-info/RECORD
