Metadata-Version: 2.1
Name: scd30_i2c
Version: 0.0.6
Summary: SCD30 CO₂ sensor Python driver
Home-page: https://github.com/RequestForCoffee/scd30
Author: RequestForCoffee
License: UNKNOWN
Platform: UNKNOWN
Classifier: Programming Language :: Python :: 3
Classifier: License :: OSI Approved :: MIT License
Classifier: Operating System :: POSIX :: Linux
Requires-Python: >=3.7.3
